euclidean/__init__.py
euclidean/approx.py
euclidean/constants.py
euclidean/exceptions.py
euclidean/util.py
euclidean/R2/__init__.py
euclidean/R2/cartesian.py
euclidean/R2/circle.py
euclidean/R2/line.py
euclidean/R2/generic/__init__.py
euclidean/R2/generic/does_intersect.py
euclidean/R2/generic/intersect.py
euclidean/R2/generic/rasterize.py
euclidean/R2/polygon/__init__.py
euclidean/R2/polygon/hull.py
euclidean/R2/polygon/line_sweep.py
euclidean/R2/polygon/polygon.py
euclidean/R3/__init__.py
euclidean/R3/cartesian.py
euclidean/R3/plane.py
euclidean/siquant/__init__.py
euclidean/siquant/factory.py
euclidean/siquant/vector.py
euclidean-1.0.0b4.dist-info/LICENSE
euclidean-1.0.0b4.dist-info/METADATA
euclidean-1.0.0b4.dist-info/WHEEL
euclidean-1.0.0b4.dist-info/top_level.txt
euclidean-1.0.0b4.dist-info/zip-safe
euclidean-1.0.0b4.dist-info/RECORD
