Metadata-Version: 2.1
Name: euclidean
Version: 1.0.0b4
Summary: Euclidean Geometry Library
Home-page: https://github.com/keystonetowersystems/euclidean
Author: Greg Echelberger
Author-email: greg@keystonetowersystems.com
License: UNKNOWN
Platform: UNKNOWN
Requires-Dist: multipledispatch (>=0.6)
Requires-Dist: sortedcontainers (>=2)
Provides-Extra: dev
Requires-Dist: coverage ; extra == 'dev'
Requires-Dist: pre-commit ; extra == 'dev'
Requires-Dist: pytest ; extra == 'dev'
Provides-Extra: docs
Provides-Extra: siquant
Requires-Dist: siquant (==4.0.0b6) ; extra == 'siquant'
Provides-Extra: tests
Requires-Dist: coverage ; extra == 'tests'
Requires-Dist: pytest ; extra == 'tests'
